{
    "dateTime": "",
    "hasError": false,
    "length": 1,
    "message": "Mock Data",
    "payload": [
        {
            "utc": "2017-01-15T00:00:00Z",
            "satellites": [

                {
                    "id": 28272,
                    "lat": 63.0989311455757,
                    "lon": 173.12451665738266,
                    "alt": 907.3502647118181
                }
               
            ],
            "vessels": [
                {
                    "id": 128272,
                    "lat": 63.0989311455757,
                    "lon": 173.12451665738266,
                    "alt": 0
                },
                {
                    "id": 367197950,
                    "lat": 53.880470008875605,
                    "lon": -141.05297233629142,
                    "alt": 0
                }
                
            ],
            "pairs": {
                "28272,367197950": {
                    "sat_id": 28272,
                    "ves_id": 367197950,
                    "azimuth": 309.8350514495879,
                    "elevation": 4.130084435271757,
                    "range": 3093.8950403330177,
                    "hit": true
                }

            }
        }
    ],
    "payloadType": "application/json",
    "metadata": null,
    "error": "",
    "errorMap": {},
    "nextPageUrl": null
}
